plugin/__init__.py
plugin/arifpay.py
ArifpayPlugin-0.0.2.dist-info/METADATA
ArifpayPlugin-0.0.2.dist-info/WHEEL
ArifpayPlugin-0.0.2.dist-info/top_level.txt
ArifpayPlugin-0.0.2.dist-info/RECORD
