Metadata-Version: 2.1
Name: ArifpayPlugin
Version: 0.0.2
Summary: Python Plug in for Arifpay
Home-page: https://github.com/AnaniyaBelew
Author: Ananiya Belew
Author-email: anewscho@gmail.com
Classifier: Programming Language :: Python :: 3.10
Classifier: Operating System :: OS Independent
Requires-Python: >=3.10
Requires-Dist: uuid
Requires-Dist: requests
Requires-Dist: python-dotenv
